numlab/__init__.py
numlab/automata/__init__.py
numlab/automata/automata.py
numlab/automata/state.py
numlab/automata/transition.py
numlab/builtin/__init__.py
numlab/builtin/nl_bool.py
numlab/builtin/nl_built_in_functions.py
numlab/builtin/nl_dict.py
numlab/builtin/nl_float.py
numlab/builtin/nl_func.py
numlab/builtin/nl_generator.py
numlab/builtin/nl_int.py
numlab/builtin/nl_list.py
numlab/builtin/nl_none.py
numlab/builtin/nl_object.py
numlab/builtin/nl_set.py
numlab/builtin/nl_slice.py
numlab/builtin/nl_str.py
numlab/builtin/nl_tuple.py
numlab/compiler/__init__.py
numlab/compiler/generic_ast.py
numlab/compiler/grammar.py
numlab/compiler/grammar_ops.py
numlab/compiler/parser_manager.py
numlab/compiler/parsers/__init__.py
numlab/compiler/parsers/lr1_parser.py
numlab/compiler/parsers/lritem.py
numlab/compiler/parsers/parser.py
numlab/compiler/terminal_set.py
numlab/compiler/tokenizer.py
numlab/exceptions.py
numlab/ia/genetic_alg.py
numlab/lang/__init__.py
numlab/lang/context.py
numlab/lang/type.py
numlab/lang/visitor.py
numlab/main.py
numlab/nl_ast.py
numlab/nl_builders.py
numlab/nl_grammar.gm
numlab/nl_lr1_table
numlab/nl_tokenizer.py
numlab/nlre.py
numlab/optimization/__init__.py
numlab/optimization/fuzzy_opt_classifier.py
numlab/optimization/optimizer.py
numlab/visitors/__init__.py
numlab/visitors/eval_visitor.py
numlab/visitors/opt_visitor.py
numlab-0.2.2.dist-info/entry_points.txt
numlab-0.2.2.dist-info/LICENSE
numlab-0.2.2.dist-info/WHEEL
numlab-0.2.2.dist-info/METADATA
numlab-0.2.2.dist-info/RECORD
