Metadata-Version: 2.1
Name: numlab
Version: 0.2.2
Summary: Programming language for analyzing mathematical numerical problem's solutions
License: MIT
Author: Jorge Morgado Vega
Author-email: jorge.morgadov@gmail.com
Requires-Python: >=3.8,<4.0
Classifier: License :: OSI Approved :: MIT License
Classifier: Programming Language :: Python :: 3
Classifier: Programming Language :: Python :: 3.10
Classifier: Programming Language :: Python :: 3.8
Classifier: Programming Language :: Python :: 3.9
Requires-Dist: typer (>=0.4.0,<0.5.0)
